k8s_user/__init__.py
k8s_user/__main__.py
k8s_user/kubeconfig.py
k8s_user/pki.py
k8s_user/user.py
k8s_user/k8s/__init__.py
k8s_user/k8s/csr_resource.py
k8s_user/k8s/sa_resource.py
k8s_user/workflows/__init__.py
k8s_user/workflows/csr_workflow.py
k8s_user/workflows/sa_workflow.py
tests/__init__.py
tests/test_k8s_user.py
tests/test_kubeconfig.py
tests/test_pki.py
tests/k8s/__init__.py
tests/k8s/test_csr_resource.py
tests/k8s/test_sa_resource.py
kubernetes_user-0.0.3.dist-info/METADATA
kubernetes_user-0.0.3.dist-info/WHEEL
kubernetes_user-0.0.3.dist-info/entry_points.txt
kubernetes_user-0.0.3.dist-info/top_level.txt
kubernetes_user-0.0.3.dist-info/RECORD
