Metadata-Version: 2.1
Name: kubernetes-user
Version: 0.0.3
Summary: A package for creating kubernetes users.
Home-page: https://github.com/JoeJasinski/k8s_user
Author: Joe Jasinski
License: UNKNOWN
Platform: UNKNOWN
Classifier: Programming Language :: Python :: 3
Classifier: License :: OSI Approved :: MIT License
Classifier: Operating System :: OS Independent
Requires-Python: >=3.6
Requires-Dist: kubernetes
Requires-Dist: cryptography
Requires-Dist: pyyaml
Provides-Extra: test
Requires-Dist: pytest ; extra == 'test'
Requires-Dist: pytest-cov ; extra == 'test'
Requires-Dist: black ; extra == 'test'
Requires-Dist: coverage ; extra == 'test'
